loader/__init__.py
loader/shiro.py
loader/swagger.py
model/__init__.py
model/tableInfo.py
so-0.5.dist-info/DESCRIPTION.rst
so-0.5.dist-info/METADATA
so-0.5.dist-info/RECORD
so-0.5.dist-info/WHEEL
so-0.5.dist-info/metadata.json
so-0.5.dist-info/top_level.txt
